setup.py
pyramid_cachebust/__init__.py
pyramid_cachebust/cachebust.py
pyramid_cachebust/tests.py
pyramid_cachebust.egg-info/PKG-INFO
pyramid_cachebust.egg-info/SOURCES.txt
pyramid_cachebust.egg-info/dependency_links.txt
pyramid_cachebust.egg-info/not-zip-safe
pyramid_cachebust.egg-info/requires.txt
pyramid_cachebust.egg-info/top_level.txt