Metadata-Version: 1.0
Name: pyramid-cachebust
Version: 0.1
Summary: Nascent cache busting for the Pyramid web framework
Home-page: https://github.com/maisano/pyramid_cachebust
Author: maisano
Author-email: rickmaisano@gmail.com
License: UNKNOWN
Keywords: web wsgi pylons pyramid cachebust
Platform: UNKNOWN
Classifier: Framework :: Pyramid
Classifier: Intended Audience :: Developers
Classifier: Programming Language :: Python
